crackest/__init__.py
crackest/crack_analyzer.py
crackest/crack_pattern_analysis.py
crackest/crack_plot.py
crackest/cracks.py
crackest/model_downloader.py
crackest/sub_spec.py
crackpy_models/__init__.py
crackenpy-0.1.69.dist-info/LICENSE
crackenpy-0.1.69.dist-info/METADATA
crackenpy-0.1.69.dist-info/WHEEL
crackenpy-0.1.69.dist-info/top_level.txt
crackenpy-0.1.69.dist-info/RECORD
