Metadata-Version: 2.1
Name: crackenpy
Version: 0.1.69
Summary: Library for detection of cracks on test specimens of building materials
Home-page: UNKNOWN
Author: Richard Dvorak, Vlastimil Bilek, Barbara Kucharczikova, Rostislav Krc
Author-email: richard.dvorak@vutbr.cz
License: UNKNOWN
Platform: UNKNOWN
License-File: LICENSE
Requires-Dist: torch>=2.0.0
Requires-Dist: pandas>=0.23.3
Requires-Dist: numpy>=1.26.0
Requires-Dist: matplotlib>=2.2.0
Requires-Dist: gdown>=5.0.0
Requires-Dist: sknw>=0.15
Requires-Dist: tqdm>=4.66.0
Requires-Dist: scikit-image>=0.21.0
Requires-Dist: scikit-learn>=0.19.1
Requires-Dist: wand>=0.6.13
Requires-Dist: segmentation-models-pytorch>=0.3.3
Requires-Dist: opencv-python>=4.8.0.76
